<?xml version="1.0" standalone="no" ?>
<!DOCTYPE pov SYSTEM "/usr/share/cgc-docs/replay.dtd">
<pov>
<cbid>service</cbid>
<replay>
    <write><data>\x05\x05\x05\x05</data></write>
    <write><data>j5</data></write>
    <read><length>2</length><match><data>\x04\x04</data></match></read>
    <write><data>\x16\x16\x16\x16</data></write>
    <read><length>2</length><match><data>\x1eD</data></match></read>
    <write><data>\x10\x10\x10\x10</data></write>
    <write><data>\xbb\xaa\xdd</data></write>
    <read><length>2</length><match><data>\x1eD</data></match></read>
    <write><data>\x10\x10\x10\x10</data></write>
    <write><data>\xbb\xaa\xdd</data></write>
    <read><length>2</length><match><data>\x1eD</data></match></read>
    <write><data>\x16\x16\x16\x16</data></write>
    <read><length>2</length><match><data>\x1eD</data></match></read>
    <write><data>\x16\x16\x16\x16</data></write>
    <read><length>2</length><match><data>\x1eD</data></match></read>
    <write><data>\x13\x13\x13\x13</data></write>
    <read><length>2</length><match><data>\x1eD</data></match></read>
    <write><data>\x12\x12\x12\x12</data></write>
    <read><length>2</length><match><data>j5</data></match></read>
    <read><length>2</length><match><data>\x04\x04</data></match></read>
    <write><data>\x11\x11\x11\x11</data></write>
    <read><length>2</length><match><data>\x1eD</data></match></read>
    <write><data>\x11\x11\x11\x11</data></write>
    <read><length>2</length><match><data>\x1eD</data></match></read>
    <write><data>\x12\x12\x12\x12</data></write>
    <read><length>2</length><match><data>j5</data></match></read>
    <read><length>2</length><match><data>\x04\x04</data></match></read>
    <write><data>\x16\x16\x16\x16</data></write>
    <read><length>2</length><match><data>\x1eD</data></match></read>
    <write><data>\x11\x11\x11\x11</data></write>
    <read><length>2</length><match><data>\x1eD</data></match></read>
    <write><data>\x10\x10\x10\x10</data></write>
    <write><data>\xbb\xaa\xdd</data></write>
    <read><length>2</length><match><data>\x1eD</data></match></read>
    <write><data>\x13\x13\x13\x13</data></write>
    <read><length>2</length><match><data>\x1eD</data></match></read>
    <write><data>\x14\x14\x14\x14</data></write>
    <read><length>2</length><match><data>\x1eD</data></match></read>
    <write><data>\x11\x11\x11\x11</data></write>
    <read><length>2</length><match><data>\x1eD</data></match></read>
    <write><data>\x03\x03\x03\x03</data></write>
    <read><length>3</length><assign> <var>stamp0</var> <slice begin="0" end="3" /> </assign></read>
    <read><length>2</length><match><data>\x04\x04</data></match></read>
    <write><data>\x15\x15\x15\x15</data></write>
    <read><length>2</length><match><data>\x1eD</data></match></read>
    <write><data>\x15\x15\x15\x15</data></write>
    <read><length>2</length><match><data>\x1eD</data></match></read>
    <write><data>\x00\x0f\xf0\xff</data></write>
    <read><length>2</length><match><data>\x04\x17</data></match></read>
</replay>
</pov>